ascii7io.py
prefscript.py
cantorpairs/__init__.py
cantorpairs/src/cantorpairs.py
cantorpairs/src/cp_ex.py
prefscript-1.1.dist-info/LICENSE
prefscript-1.1.dist-info/METADATA
prefscript-1.1.dist-info/WHEEL
prefscript-1.1.dist-info/entry_points.txt
prefscript-1.1.dist-info/top_level.txt
prefscript-1.1.dist-info/RECORD
