Metadata-Version: 2.1
Name: prefscript
Version: 1.1
Summary: Partial Recursive Functions for Scripting
Author-email: José Luis Balcázar <jose.luis.balcazar@upc.edu>
Project-URL: Homepage, https://github.com/balqui/prefscript
Project-URL: Bug Tracker, https://github.com/balqui/prefscript/issues
Classifier: Programming Language :: Python :: 3
Classifier: License :: OSI Approved :: MIT License
Classifier: Operating System :: OS Independent
Requires-Python: >=3.10
License-File: LICENSE
Requires-Dist: pytokr >=1.0
